zq145_mcp_server_ex0804/__init__.py
zq145_mcp_server_ex0804-0.1.0.dist-info/WHEEL
zq145_mcp_server_ex0804-0.1.0.dist-info/entry_points.txt
zq145_mcp_server_ex0804-0.1.0.dist-info/METADATA
zq145_mcp_server_ex0804-0.1.0.dist-info/RECORD
